bomiot_process/__init__.py
bomiot_process/process.py
bomiot_process/process.toml
bomiot_process/stoppid.py
LICENSE
bomiot_process-0.9.10.dist-info/LICENSE
bomiot_process-0.9.10.dist-info/METADATA
bomiot_process-0.9.10.dist-info/WHEEL
bomiot_process-0.9.10.dist-info/RECORD
